odoo/addons/mail_activity_done/README.rst
odoo/addons/mail_activity_done/__init__.py
odoo/addons/mail_activity_done/__manifest__.py
odoo/addons/mail_activity_done/hooks.py
odoo/addons/mail_activity_done/i18n/de.po
odoo/addons/mail_activity_done/i18n/es.po
odoo/addons/mail_activity_done/i18n/fi.po
odoo/addons/mail_activity_done/i18n/fr.po
odoo/addons/mail_activity_done/i18n/hu.po
odoo/addons/mail_activity_done/i18n/it.po
odoo/addons/mail_activity_done/i18n/mail_activity_done.pot
odoo/addons/mail_activity_done/migrations/18.0.1.0.0/post-migration.py
odoo/addons/mail_activity_done/models/__init__.py
odoo/addons/mail_activity_done/models/mail_activity_type.py
odoo/addons/mail_activity_done/readme/CONTRIBUTORS.md
odoo/addons/mail_activity_done/readme/DESCRIPTION.md
odoo/addons/mail_activity_done/readme/USAGE.md
odoo/addons/mail_activity_done/static/description/icon.png
odoo/addons/mail_activity_done/static/description/index.html
odoo/addons/mail_activity_done/tests/__init__.py
odoo/addons/mail_activity_done/tests/test_mail_activity_done.py
odoo_addon_mail_activity_done-18.0.1.0.0.4.dist-info/METADATA
odoo_addon_mail_activity_done-18.0.1.0.0.4.dist-info/WHEEL
odoo_addon_mail_activity_done-18.0.1.0.0.4.dist-info/top_level.txt
odoo_addon_mail_activity_done-18.0.1.0.0.4.dist-info/RECORD
